ModulationPy/ModulationPy.py
ModulationPy/__init__.py
ModulationPy-0.1.8.dist-info/LICENSE
ModulationPy-0.1.8.dist-info/METADATA
ModulationPy-0.1.8.dist-info/WHEEL
ModulationPy-0.1.8.dist-info/top_level.txt
ModulationPy-0.1.8.dist-info/RECORD
