Metadata-Version: 2.1
Name: ModulationPy
Version: 0.1.8
Summary: Baseband Digital Linear Modems
Home-page: https://github.com/kirlf/ModulationPy
Author: Vladimir Fadeev
Author-email: vovenur@gmail.com
License: BSD 3-Clause
Keywords: communications digital modulation demodulation psk qam
Platform: UNKNOWN
Classifier: License :: OSI Approved :: BSD License
Classifier: Programming Language :: Python :: 3.6
Classifier: Intended Audience :: Science/Research
Classifier: Intended Audience :: Telecommunications Industry
Classifier: Operating System :: Unix
Classifier: Topic :: Scientific/Engineering
Classifier: Topic :: Software Development
Requires-Python: >=3.6.4
Requires-Dist: numpy (>=1.7.1)
Requires-Dist: matplotlib (>=2.2.2)
